Workbook

Sheet Dashboard
A1: GHG Inventory Dashboard
A2: All totals below are formula-driven and only include Scope 3 categories marked 'Included' in Materiality_Screening.
A4: Scope 1 (tCO2e) | B4: =GHG_Calculator!F22
A5: Scope 2 - Location-Based (tCO2e) | B5: =GHG_Calculator!F32
A6: Scope 2 - Market-Based (tCO2e) | B6: =GHG_Calculator!F39
A7: Scope 3, Categories 1-9 (tCO2e, materiality-filtered) | B7: =SUM(GHG_Calculator!F42:F92)
A8: Scope 3, Categories 10-15 (tCO2e) | B8: =Scope3_Hard_Categories!B53
A10: GRAND TOTAL - Location-Based Scope 2 (tCO2e) | B10: =B4+B5+B7+B8
A11: GRAND TOTAL - Market-Based Scope 2 (tCO2e) | B11: =B4+B6+B7+B8
A13: Rows still flagged (unassessed quantity or zero factor)
A14: =COUNTIF(GHG_Calculator!G2:G92,"?*") | B14: ="Open the GHG_Calculator tab -> Flag column to see which rows"
A16: Excluded / Not Applicable Scope 3 categories (with reason)
A17: Category | B17: Decision | C17: Justification
A18: =IF(Materiality_Screening!D2<>"Included",Materiality_Screening!B2,"") | B18: =IF(Materiality_Screening!D2<>"Included",Materiality_Screening!D2,"") | C18: =IF(Materiality_Screening!D2<>"Included",Materiality_Screening!E2,"")
A19: =IF(Materiality_Screening!D3<>"Included",Materiality_Screening!B3,"") | B19: =IF(Materiality_Screening!D3<>"Included",Materiality_Screening!D3,"") | C19: =IF(Materiality_Screening!D3<>"Included",Materiality_Screening!E3,"")
A20: =IF(Materiality_Screening!D4<>"Included",Materiality_Screening!B4,"") | B20: =IF(Materiality_Screening!D4<>"Included",Materiality_Screening!D4,"") | C20: =IF(Materiality_Screening!D4<>"Included",Materiality_Screening!E4,"")
A21: =IF(Materiality_Screening!D5<>"Included",Materiality_Screening!B5,"") | B21: =IF(Materiality_Screening!D5<>"Included",Materiality_Screening!D5,"") | C21: =IF(Materiality_Screening!D5<>"Included",Materiality_Screening!E5,"")
A22: =IF(Materiality_Screening!D6<>"Included",Materiality_Screening!B6,"") | B22: =IF(Materiality_Screening!D6<>"Included",Materiality_Screening!D6,"") | C22: =IF(Materiality_Screening!D6<>"Included",Materiality_Screening!E6,"")
A23: =IF(Materiality_Screening!D7<>"Included",Materiality_Screening!B7,"") | B23: =IF(Materiality_Screening!D7<>"Included",Materiality_Screening!D7,"") | C23: =IF(Materiality_Screening!D7<>"Included",Materiality_Screening!E7,"")
A24: =IF(Materiality_Screening!D8<>"Included",Materiality_Screening!B8,"") | B24: =IF(Materiality_Screening!D8<>"Included",Materiality_Screening!D8,"") | C24: =IF(Materiality_Screening!D8<>"Included",Materiality_Screening!E8,"")
A25: =IF(Materiality_Screening!D9<>"Included",Materiality_Screening!B9,"") | B25: =IF(Materiality_Screening!D9<>"Included",Materiality_Screening!D9,"") | C25: =IF(Materiality_Screening!D9<>"Included",Materiality_Screening!E9,"")
A26: =IF(Materiality_Screening!D10<>"Included",Materiality_Screening!B10,"") | B26: =IF(Materiality_Screening!D10<>"Included",Materiality_Screening!D10,"") | C26: =IF(Materiality_Screening!D10<>"Included",Materiality_Screening!E10,"")
A27: =IF(Materiality_Screening!D11<>"Included",Materiality_Screening!B11,"") | B27: =IF(Materiality_Screening!D11<>"Included",Materiality_Screening!D11,"") | C27: =IF(Materiality_Screening!D11<>"Included",Materiality_Screening!E11,"")
A28: =IF(Materiality_Screening!D12<>"Included",Materiality_Screening!B12,"") | B28: =IF(Materiality_Screening!D12<>"Included",Materiality_Screening!D12,"") | C28: =IF(Materiality_Screening!D12<>"Included",Materiality_Screening!E12,"")
A29: =IF(Materiality_Screening!D13<>"Included",Materiality_Screening!B13,"") | B29: =IF(Materiality_Screening!D13<>"Included",Materiality_Screening!D13,"") | C29: =IF(Materiality_Screening!D13<>"Included",Materiality_Screening!E13,"")
... A32: =IF(Materiality_Screening!D16<>"Included",Materiality_Screening!B16,"") | B32: =IF(Materiality_Screening!D16<>"Included",Materiality_Screening!D16,"") | C32: =IF(Materiality_Screening!D16<>"Included",Materiality_Screening!E16,"")

Sheet Cover_Boundary
A1: GHG Emissions Inventory - Boundary & Reporting Basis
A3: 1. Reporting Entity
A4: Company / Facility Name | D4: Legal entity or facility this inventory covers
A5: Reporting Period | D5: e.g. 1 Apr 2025 - 31 Mar 2026
A6: Base Year | D6: REQUIRED for tracking reductions over time - GHG Protocol mandates a fixed base year
A7: Prepared By / Contact
A8: Date of Preparation
A10: 2. Organizational Boundary (choose ONE consolidation approach)
A11: Consolidation Approach | B11: Select one | D11: Determines which facilities/entities are consolidated into this inventory - see GHG Protocol Corporate Standard Ch.3
A12: Entities/Facilities Included | D12: List every facility or subsidiary consolidated under the chosen approach
A13: Entities/Facilities Explicitly Excluded | D13: Document any exclusion and the reason (e.g. divested, immaterial, no operational control)
A15: 3. Operational Boundary (which scopes are covered)
A16: Scope 1 (Direct Emissions) | B16: Included
A17: Scope 2 (Purchased Energy) | B17: Included
A18: Scope 3 (Value Chain) | B18: Included
A19: Scope 3 Categories Excluded (if any) | D19: List category numbers 1-15 excluded and justification - see GHG_Master_Calculator tab for the full category list
A21: 4. Methodology & Standards Applied
A22: Primary Standard | B22: GHG Protocol Corporate Standard + Corporate Value Chain (Scope 3) Standard | D22: e.g. GHG Protocol Corporate Standard + Scope 3 Standard; or ISO 14064-1
A23: GWP Values Used | B23: IPCC AR4 (verify against your disclosure framework's required vintage) | D23: Confirm IPCC Assessment Report vintage - see DB_Master notes column for per-factor citations
A24: Scope 2 Reporting Method | B24: Dual reporting: Location-based + Market-based (see GHG_Master_Calculator) | D24: GHG Protocol Scope 2 Guidance requires BOTH methods where applicable
A26: 5. Assurance Status
A27: Third-Party Verification Status | D27: e.g. Not yet verified / Limited assurance / Reasonable assurance, and by whom
A28: Data Quality Approach | D28: Every line item in GHG_Master_Calculator has a Data Quality tier - see that tab
A30: 6. Materiality & Exclusion Policy
A31: Materiality Threshold | D31: e.g. 5% of total inventory, or an absolute tCO2e cutoff -- state the basis for excluding immaterial sources
A32: Sources Excluded as Immaterial | D32: List any emission source knowingly left out because it falls below the materiality threshold, with rationale
A33: CO2e Conversion Note | D33: Confirm whether Scope 1/2 combustion factors used are CO2-only or full CO2e -- see DB_Master notes column per factor
A35: 7. Version History
A36: Version | B36: Date | C36: Changes
A37: v5 | C37: CO2e labeling correction; materiality/exclusion fields added

Sheet DB_Master
A1: Lookup Key | B1: Emission Factor | C1: Source / Notes | D1: Automation Status
A2: Diesel_Fuel | B2: 2.6558 | C2: India GHG Program base CO2 factor (2.64) + ~0.6% CH4/N2O uplift per US EPA GHG Equivalencies methodology (2024) = 2.6558 kgCO2e -- uplift is a documented approximation (CO2 is >99% of combustion CO2e per EPA), not an India-specific measured N2O/CH4 split | D2: Fixed Factor
A3: Petrol_Fuel | B3: 2.2836 | C3: India GHG Program base CO2 factor (2.27) + ~0.6% CH4/N2O uplift per US EPA GHG Equivalencies methodology (2024) = 2.2836 kgCO2e -- uplift is a documented approximation (CO2 is >99% of combustion CO2e per EPA), not an India-specific measured N2O/CH4 split | D3: Fixed Factor
A4: CNG_Fuel | B4: 2.686 | C4: India GHG Program base CO2 factor (2.67) + ~0.6% CH4/N2O uplift per US EPA GHG Equivalencies methodology (2024) = 2.686 kgCO2e -- uplift is a documented approximation (CO2 is >99% of combustion CO2e per EPA), not an India-specific measured N2O/CH4 split | D4: Fixed Factor
A5: LPG_Commercial | B5: 2.9979 | C5: India GHG Program base CO2 factor (2.98) + ~0.6% CH4/N2O uplift per US EPA GHG Equivalencies methodology (2024) = 2.9979 kgCO2e -- uplift is a documented approximation (CO2 is >99% of combustion CO2e per EPA), not an India-specific measured N2O/CH4 split | D5: Fixed Factor
A6: Coal_Indian | B6: 1.9919 | C6: India GHG Program base CO2 factor (1.98) + ~0.6% CH4/N2O uplift per US EPA GHG Equivalencies methodology (2024) = 1.9919 kgCO2e -- uplift is a documented approximation (CO2 is >99% of combustion CO2e per EPA), not an India-specific measured N2O/CH4 split | D6: Fixed Factor
A7: Furnace_Oil | B7: 3.1186 | C7: India GHG Program base CO2 factor (3.1) + ~0.6% CH4/N2O uplift per US EPA GHG Equivalencies methodology (2024) = 3.1186 kgCO2e -- uplift is a documented approximation (CO2 is >99% of combustion CO2e per EPA), not an India-specific measured N2O/CH4 split | D7: Fixed Factor
A8: Natural_Gas | B8: 1.8913 | C8: India GHG Program base CO2 factor (1.88) + ~0.6% CH4/N2O uplift per US EPA GHG Equivalencies methodology (2024) = 1.8913 kgCO2e -- uplift is a documented approximation (CO2 is >99% of combustion CO2e per EPA), not an India-specific measured N2O/CH4 split | D8: Fixed Factor
A9: Acetylene_Welding | B9: 3.4003 | C9: India GHG Program base CO2 factor (3.38) + ~0.6% CH4/N2O uplift per US EPA GHG Equivalencies methodology (2024) = 3.4003 kgCO2e -- uplift is a documented approximation (CO2 is >99% of combustion CO2e per EPA), not an India-specific measured N2O/CH4 split | D9: Fixed Factor
A10: Fire_Extinguisher_CO2 | B10: 1 | C10: GWP of CO2 = 1, all AR vintages (kgCO2e/kg) | D10: Fixed Factor
A11: Refrig_R32 | B11: 675 | C11: IPCC AR4 GWP-100 (kgCO2e/kg) -- verify vintage required by your framework | D11: Fixed Factor
A12: Refrig_R410A | B12: 2088 | C12: IPCC AR4 GWP-100 (kgCO2e/kg) -- verify vintage required by your framework | D12: Fixed Factor
A13: Refrig_R22 | B13: 1810 | C13: IPCC AR4 GWP-100 (kgCO2e/kg) -- verify vintage required by your framework | D13: Fixed Factor
... A55: Financed_Emissions_Passthrough | B55: 1 | C55: Direct pass-through of reported financed emissions (tCO2e/tCO2e) | D55: Fixed Factor
A57: Note: six placeholder factors from v6 (Product_Use_Phase_Energy, Product_EndOfLife, Investment_Equity_Share, Franchise_Estimate, Leased_Asset_Downstream, Processing_Sold_Products_Proxy) have been removed from this table. A single generic factor cannot legitimately represent these — see the Scope3_Hard_Categories tab, where each is replaced with a formula driven by your own company/product data.

Sheet GHG_Calculator
A1: Category / Item | B1: Quantity (Input) | C1: Unit | D1: Emission Factor (live) | E1: Data Quality | F1: Result (tCO2e) | G1: Flag
A2: SCOPE 1 - DIRECT EMISSIONS
A3: Category / Item | B3: Quantity (Input) | C3: Unit | D3: Emission Factor (live) | E3: Data Quality | F3: Result (tCO2e) | G3: Flag
A4: Stationary Combustion | B4: 0 | E4: Not Yet Assessed
A5: Diesel Generator (DG Sets) | B5: 0 | C5: Liters | D5: 2.6558 | E5: Not Yet Assessed | F5: =IF(B5=0,0,(B5*2.6558)/1000) | G5: =IF(AND(B5>0,E5="Not Yet Assessed"),"Quantity entered but Data Quality not assessed",IF(AND(B5>0,D5=0),"Zero emission factor - check DB_Master",""))
A6: Furnace Oil (Boilers) | B6: 0 | C6: Liters | D6: 3.1186 | E6: Not Yet Assessed | F6: =IF(B6=0,0,(B6*3.1186)/1000) | G6: =IF(AND(B6>0,E6="Not Yet Assessed"),"Quantity entered but Data Quality not assessed",IF(AND(B6>0,D6=0),"Zero emission factor - check DB_Master",""))
A7: Natural Gas | B7: 0 | C7: scm | D7: 1.8913 | E7: Not Yet Assessed | F7: =IF(B7=0,0,(B7*1.8913)/1000) | G7: =IF(AND(B7>0,E7="Not Yet Assessed"),"Quantity entered but Data Quality not assessed",IF(AND(B7>0,D7=0),"Zero emission factor - check DB_Master",""))
A8: Indian Coal (Boilers) | B8: 0 | C8: kg | D8: 1.9919 | E8: Not Yet Assessed | F8: =IF(B8=0,0,(B8*1.9919)/1000) | G8: =IF(AND(B8>0,E8="Not Yet Assessed"),"Quantity entered but Data Quality not assessed",IF(AND(B8>0,D8=0),"Zero emission factor - check DB_Master",""))
A9: Commercial LPG | B9: 0 | C9: kg | D9: 2.9979 | E9: Not Yet Assessed | F9: =IF(B9=0,0,(B9*2.9979)/1000) | G9: =IF(AND(B9>0,E9="Not Yet Assessed"),"Quantity entered but Data Quality not assessed",IF(AND(B9>0,D9=0),"Zero emission factor - check DB_Master",""))
A10: Mobile Combustion (Owned/Leased Vehicles)
A11: Petrol Company Cars | B11: 0 | C11: Liters | D11: 2.2836 | E11: Not Yet Assessed | F11: =IF(B11=0,0,(B11*2.2836)/1000) | G11: =IF(AND(B11>0,E11="Not Yet Assessed"),"Quantity entered but Data Quality not assessed",IF(AND(B11>0,D11=0),"Zero emission factor - check DB_Master",""))
A12: Diesel Company Vehicles | B12: 0 | C12: Liters | D12: 2.6558 | E12: Not Yet Assessed | F12: =IF(B12=0,0,(B12*2.6558)/1000) | G12: =IF(AND(B12>0,E12="Not Yet Assessed"),"Quantity entered but Data Quality not assessed",IF(AND(B12>0,D12=0),"Zero emission factor - check DB_Master",""))
A13: CNG Vehicles | B13: 0 | C13: kg | D13: 2.686 | E13: Not Yet Assessed | F13: =IF(B13=0,0,(B13*2.686)/1000) | G13: =IF(AND(B13>0,E13="Not Yet Assessed"),"Quantity entered but Data Quality not assessed",IF(AND(B13>0,D13=0),"Zero emission factor - check DB_Master",""))
A14: Fugitive Emissions
A15: Refrigerant Top-up - R-32 | B15: 0 | C15: kg | D15: 675 | E15: Not Yet Assessed | F15: =IF(B15=0,0,(B15*675.0)/1000) | G15: =IF(AND(B15>0,E15="Not Yet Assessed"),"Quantity entered but Data Quality not assessed",IF(AND(B15>0,D15=0),"Zero emission factor - check DB_Master",""))
A16: Refrigerant Top-up - R-410A | B16: 0 | C16: kg | D16: 2088 | E16: Not Yet Assessed | F16: =IF(B16=0,0,(B16*2088.0)/1000) | G16: =IF(AND(B16>0,E16="Not Yet Assessed"),"Quantity entered but Data Quality not assessed",IF(AND(B16>0,D16=0),"Zero emission factor - check DB_Master",""))
A17: Refrigerant Top-up - R-22 | B17: 0 | C17: kg | D17: 1810 | E17: Not Yet Assessed | F17: =IF(B17=0,0,(B17*1810.0)/1000) | G17: =IF(AND(B17>0,E17="Not Yet Assessed"),"Quantity entered but Data Quality not assessed",IF(AND(B17>0,D17=0),"Zero emission factor - check DB_Master",""))
A18: Process Emissions
A19: Acetylene Welding | B19: 0 | C19: kg | D19: 3.4003 | E19: Not Yet Assessed | F19: =IF(B19=0,0,(B19*3.4003)/1000) | G19: =IF(AND(B19>0,E19="Not Yet Assessed"),"Quantity entered but Data Quality not assessed",IF(AND(B19>0,D19=0),"Zero emission factor - check DB_Master",""))
A20: CO2 Fire Extinguisher Discharge | B20: 0 | C20: kg | D20: 1 | E20: Not Yet Assessed | F20: =IF(B20=0,0,(B20*1.0)/1000) | G20: =IF(AND(B20>0,E20="Not Yet Assessed"),"Quantity entered but Data Quality not assessed",IF(AND(B20>0,D20=0),"Zero emission factor - check DB_Master",""))
A22: SCOPE 1 TOTAL | F22: =SUM(F3:F21)
A24: SCOPE 2 - PURCHASED ENERGY (Dual Reporting per GHG Protocol Scope 2 Guidance)
A25: Category / Item | B25: Quantity (Input) | C25: Unit | D25: Emission Factor (live) | E25: Data Quality | F25: Result (tCO2e) | G25: Flag
A26: Location-Based Method (grid average emission factor)
A27: Office Electricity - Grid Average | B27: 0 | C27: kWh | D27: 0.7314 | E27: Not Yet Assessed | F27: =IF(B27=0,0,(B27*0.7314)/1000) | G27: =IF(AND(B27>0,E27="Not Yet Assessed"),"Quantity entered but Data Quality not assessed",IF(AND(B27>0,D27=0),"Zero emission factor - check DB_Master",""))
A28: Factory Electricity - Grid Average | B28: 0 | C28: kWh | D28: 0.7314 | E28: Not Yet Assessed | F28: =IF(B28=0,0,(B28*0.7314)/1000) | G28: =IF(AND(B28>0,E28="Not Yet Assessed"),"Quantity entered but Data Quality not assessed",IF(AND(B28>0,D28=0),"Zero emission factor - check DB_Master",""))
A29: Warehouse Electricity - Grid Average | B29: 0 | C29: kWh | D29: 0.7314 | E29: Not Yet Assessed | F29: =IF(B29=0,0,(B29*0.7314)/1000) | G29: =IF(AND(B29>0,E29="Not Yet Assessed"),"Quantity entered but Data Quality not assessed",IF(AND(B29>0,D29=0),"Zero emission factor - check DB_Master",""))
A30: Purchased Steam | B30: 0 | C30: kg | D30: 0.1811 | E30: Not Yet Assessed | F30: =IF(B30=0,0,(B30*0.1811)/1000) | G30: =IF(AND(B30>0,E30="Not Yet Assessed"),"Quantity entered but Data Quality not assessed",IF(AND(B30>0,D30=0),"Zero emission factor - check DB_Master",""))
A32: SCOPE 2 TOTAL (Location-Based) | F32: =SUM(F25:F31)
A34: Market-Based Method (supplier-specific / REC / residual mix)
A35: Office Electricity - Supplier/Residual Mix | B35: 0 | C35: kWh | D35: 0.7314 | E35: Not Yet Assessed | F35: =IF(B35=0,0,(B35*0.7314)/1000) | G35: =IF(AND(B35>0,E35="Not Yet Assessed"),"Quantity entered but Data Quality not assessed",IF(AND(B35>0,D35=0),"Zero emission factor - check DB_Master",""))
A36: Factory Electricity - Supplier/Residual Mix | B36: 0 | C36: kWh | D36: 0.7314 | E36: Not Yet Assessed | F36: =IF(B36=0,0,(B36*0.7314)/1000) | G36: =IF(AND(B36>0,E36="Not Yet Assessed"),"Quantity entered but Data Quality not assessed",IF(AND(B36>0,D36=0),"Zero emission factor - check DB_Master",""))
A37: Renewable/REC-Backed Electricity Purchased | B37: 0 | C37: kWh | D37: 0 | E37: Not Yet Assessed | F37: =IF(B37=0,0,(B37*0.0)/1000) | G37: =IF(AND(B37>0,E37="Not Yet Assessed"),"Quantity entered but Data Quality not assessed",IF(AND(B37>0,D37=0),"Zero emission factor - check DB_Master",""))
A39: SCOPE 2 TOTAL (Market-Based) | F39: =SUM(F33:F38)
A41: SCOPE 3 - VALUE CHAIN (all 15 GHG Protocol categories)
A42: Category / Item | B42: Quantity (Input) | C42: Unit | D42: Emission Factor (live) | E42: Data Quality | F42: Result (tCO2e) | G42: Flag
A43: Category 1: Purchased Goods & Services
A44: IT / Professional Services (Spend) | B44: 0 | C44: INR | D44: 0.005 | E44: Not Yet Assessed | F44: =IF(B44=0,0,(B44*0.005)/1000) | G44: =IF(AND(B44>0,E44="Not Yet Assessed"),"Quantity entered but Data Quality not assessed",IF(AND(B44>0,D44=0),"Zero emission factor - check DB_Master",""))
A45: Construction / Repairs (Spend) | B45: 0 | C45: INR | D45: 0.012 | E45: Not Yet Assessed | F45: =IF(B45=0,0,(B45*0.012)/1000) | G45: =IF(AND(B45>0,E45="Not Yet Assessed"),"Quantity entered but Data Quality not assessed",IF(AND(B45>0,D45=0),"Zero emission factor - check DB_Master",""))
A46: Generic Purchased Services (Spend) | B46: 0 | C46: INR | D46: 0.003 | E46: Not Yet Assessed | F46: =IF(B46=0,0,(B46*0.003)/1000) | G46: =IF(AND(B46>0,E46="Not Yet Assessed"),"Quantity entered but Data Quality not assessed",IF(AND(B46>0,D46=0),"Zero emission factor - check DB_Master",""))
A47: Virgin Paper Procurement | B47: 0 | C47: kg | D47: 0.92 | E47: Not Yet Assessed | F47: =IF(B47=0,0,(B47*0.92)/1000) | G47: =IF(AND(B47>0,E47="Not Yet Assessed"),"Quantity entered but Data Quality not assessed",IF(AND(B47>0,D47=0),"Zero emission factor - check DB_Master",""))
A48: Recycled Paper Procurement | B48: 0 | C48: kg | D48: 0.6 | E48: Not Yet Assessed | F48: =IF(B48=0,0,(B48*0.6)/1000) | G48: =IF(AND(B48>0,E48="Not Yet Assessed"),"Quantity entered but Data Quality not assessed",IF(AND(B48>0,D48=0),"Zero emission factor - check DB_Master",""))
A49: Plastic Packaging Procurement | B49: 0 | C49: kg | D49: 2.5 | E49: Not Yet Assessed | F49: =IF(B49=0,0,(B49*2.5)/1000) | G49: =IF(AND(B49>0,E49="Not Yet Assessed"),"Quantity entered but Data Quality not assessed",IF(AND(B49>0,D49=0),"Zero emission factor - check DB_Master",""))
A50: Construction Steel Procurement | B50: 0 | C50: kg | D50: 2.33 | E50: Not Yet Assessed | F50: =IF(B50=0,0,(B50*2.33)/1000) | G50: =IF(AND(B50>0,E50="Not Yet Assessed"),"Quantity entered but Data Quality not assessed",IF(AND(B50>0,D50=0),"Zero emission factor - check DB_Master",""))
A51: Cement Procurement | B51: 0 | C51: kg | D51: 0.9 | E51: Not Yet Assessed | F51: =IF(B51=0,0,(B51*0.9)/1000) | G51: =IF(AND(B51>0,E51="Not Yet Assessed"),"Quantity entered but Data Quality not assessed",IF(AND(B51>0,D51=0),"Zero emission factor - check DB_Master",""))
A52: Category 2: Capital Goods
A53: Laptops Purchased | B53: 0 | C53: Units | D53: 250 | E53: Not Yet Assessed | F53: =IF(B53=0,0,(B53*250.0)/1000) | G53: =IF(AND(B53>0,E53="Not Yet Assessed"),"Quantity entered but Data Quality not assessed",IF(AND(B53>0,D53=0),"Zero emission factor - check DB_Master",""))
A54: Desktops Purchased | B54: 0 | C54: Units | D54: 350 | E54: Not Yet Assessed | F54: =IF(B54=0,0,(B54*350.0)/1000) | G54: =IF(AND(B54>0,E54="Not Yet Assessed"),"Quantity entered but Data Quality not assessed",IF(AND(B54>0,D54=0),"Zero emission factor - check DB_Master",""))
A55: Smartphones Purchased | B55: 0 | C55: Units | D55: 65 | E55: Not Yet Assessed | F55: =IF(B55=0,0,(B55*65.0)/1000) | G55: =IF(AND(B55>0,E55="Not Yet Assessed"),"Quantity entered but Data Quality not assessed",IF(AND(B55>0,D55=0),"Zero emission factor - check DB_Master",""))
A56: Office Furniture Purchased | B56: 0 | C56: kg | D56: 3.5 | E56: Not Yet Assessed | F56: =IF(B56=0,0,(B56*3.5)/1000) | G56: =IF(AND(B56>0,E56="Not Yet Assessed"),"Quantity entered but Data Quality not assessed",IF(AND(B56>0,D56=0),"Zero emission factor - check DB_Master",""))
A57: Category 3: Fuel- and Energy-Related Activities (not in Scope 1/2)
A58: Well-to-Tank: Diesel | B58: 0 | C58: Liters | D58: 0.5835 | E58: Not Yet Assessed | F58: =IF(B58=0,0,(B58*0.5835)/1000) | G58: =IF(AND(B58>0,E58="Not Yet Assessed"),"Quantity entered but Data Quality not assessed",IF(AND(B58>0,D58=0),"Zero emission factor - check DB_Master",""))
A59: Well-to-Tank: Petrol | B59: 0 | C59: Liters | D59: 0.4628 | E59: Not Yet Assessed | F59: =IF(B59=0,0,(B59*0.4628)/1000) | G59: =IF(AND(B59>0,E59="Not Yet Assessed"),"Quantity entered but Data Quality not assessed",IF(AND(B59>0,D59=0),"Zero emission factor - check DB_Master",""))
A60: Grid T&D Losses | B60: 0 | C60: kWh | D60: 0.1459 | E60: Not Yet Assessed | F60: =IF(B60=0,0,(B60*0.1459)/1000) | G60: =IF(AND(B60>0,E60="Not Yet Assessed"),"Quantity entered but Data Quality not assessed",IF(AND(B60>0,D60=0),"Zero emission factor - check DB_Master",""))
A61: Category 4: Upstream Transportation & Distribution
A62: Inbound Trucking (Diesel, tonne-km) | B62: 0 | C62: tonne-km | D62: 0.09 | E62: Not Yet Assessed | F62: =IF(B62=0,0,(B62*0.09)/1000) | G62: =IF(AND(B62>0,E62="Not Yet Assessed"),"Quantity entered but Data Quality not assessed",IF(AND(B62>0,D62=0),"Zero emission factor - check DB_Master",""))
A63: Inbound LCV Delivery | B63: 0 | C63: km | D63: 0.45 | E63: Not Yet Assessed | F63: =IF(B63=0,0,(B63*0.45)/1000) | G63: =IF(AND(B63>0,E63="Not Yet Assessed"),"Quantity entered but Data Quality not assessed",IF(AND(B63>0,D63=0),"Zero emission factor - check DB_Master",""))
A64: Inbound HGV Delivery | B64: 0 | C64: km | D64: 0.85 | E64: Not Yet Assessed | F64: =IF(B64=0,0,(B64*0.85)/1000) | G64: =IF(AND(B64>0,E64="Not Yet Assessed"),"Quantity entered but Data Quality not assessed",IF(AND(B64>0,D64=0),"Zero emission factor - check DB_Master",""))
A65: Inbound Rail Freight | B65: 0 | C65: tonne-km | D65: 0.015 | E65: Not Yet Assessed | F65: =IF(B65=0,0,(B65*0.015)/1000) | G65: =IF(AND(B65>0,E65="Not Yet Assessed"),"Quantity entered but Data Quality not assessed",IF(AND(B65>0,D65=0),"Zero emission factor - check DB_Master",""))
A66: Inbound Air Freight | B66: 0 | C66: tonne-km | D66: 1.58 | E66: Not Yet Assessed | F66: =IF(B66=0,0,(B66*1.58)/1000) | G66: =IF(AND(B66>0,E66="Not Yet Assessed"),"Quantity entered but Data Quality not assessed",IF(AND(B66>0,D66=0),"Zero emission factor - check DB_Master",""))
A67: Category 5: Waste Generated in Operations
A68: Waste to Landfill | B68: 0 | C68: kg | D68: 0.85 | E68: Not Yet Assessed | F68: =IF(B68=0,0,(B68*0.85)/1000) | G68: =IF(AND(B68>0,E68="Not Yet Assessed"),"Quantity entered but Data Quality not assessed",IF(AND(B68>0,D68=0),"Zero emission factor - check DB_Master",""))
A69: Waste Recycled | B69: 0 | C69: kg | D69: 0.021 | E69: Not Yet Assessed | F69: =IF(B69=0,0,(B69*0.021)/1000) | G69: =IF(AND(B69>0,E69="Not Yet Assessed"),"Quantity entered but Data Quality not assessed",IF(AND(B69>0,D69=0),"Zero emission factor - check DB_Master",""))
A70: Waste Incinerated | B70: 0 | C70: kg | D70: 0.4 | E70: Not Yet Assessed | F70: =IF(B70=0,0,(B70*0.4)/1000) | G70: =IF(AND(B70>0,E70="Not Yet Assessed"),"Quantity entered but Data Quality not assessed",IF(AND(B70>0,D70=0),"Zero emission factor - check DB_Master",""))
A71: Wastewater Treated | B71: 0 | C71: m3 | D71: 0.708 | E71: Not Yet Assessed | F71: =IF(B71=0,0,(B71*0.708)/1000) | G71: =IF(AND(B71>0,E71="Not Yet Assessed"),"Quantity entered but Data Quality not assessed",IF(AND(B71>0,D71=0),"Zero emission factor - check DB_Master",""))
A72: Category 6: Business Travel
A73: Domestic Flights | B73: 0 | C73: p-km | D73: 0.12 | E73: Not Yet Assessed | F73: =IF(B73=0,0,(B73*0.12)/1000) | G73: =IF(AND(B73>0,E73="Not Yet Assessed"),"Quantity entered but Data Quality not assessed",IF(AND(B73>0,D73=0),"Zero emission factor - check DB_Master",""))
A74: International Flights | B74: 0 | C74: p-km | D74: 0.117 | E74: Not Yet Assessed | F74: =IF(B74=0,0,(B74*0.117)/1000) | G74: =IF(AND(B74>0,E74="Not Yet Assessed"),"Quantity entered but Data Quality not assessed",IF(AND(B74>0,D74=0),"Zero emission factor - check DB_Master",""))
A75: Rail Travel | B75: 0 | C75: p-km | D75: 0.01 | E75: Not Yet Assessed | F75: =IF(B75=0,0,(B75*0.01)/1000) | G75: =IF(AND(B75>0,E75="Not Yet Assessed"),"Quantity entered but Data Quality not assessed",IF(AND(B75>0,D75=0),"Zero emission factor - check DB_Master",""))
A76: Taxi Travel | B76: 0 | C76: km | D76: 0.14 | E76: Not Yet Assessed | F76: =IF(B76=0,0,(B76*0.14)/1000) | G76: =IF(AND(B76>0,E76="Not Yet Assessed"),"Quantity entered but Data Quality not assessed",IF(AND(B76>0,D76=0),"Zero emission factor - check DB_Master",""))
A77: Hotel Nights - 5 Star | B77: 0 | C77: Nights | D77: 75.5 | E77: Not Yet Assessed | F77: =IF(B77=0,0,(B77*75.5)/1000) | G77: =IF(AND(B77>0,E77="Not Yet Assessed"),"Quantity entered but Data Quality not assessed",IF(AND(B77>0,D77=0),"Zero emission factor - check DB_Master",""))
A78: Hotel Nights - Budget | B78: 0 | C78: Nights | D78: 25 | E78: Not Yet Assessed | F78: =IF(B78=0,0,(B78*25.0)/1000) | G78: =IF(AND(B78>0,E78="Not Yet Assessed"),"Quantity entered but Data Quality not assessed",IF(AND(B78>0,D78=0),"Zero emission factor - check DB_Master",""))
A79: Category 7: Employee Commuting
A80: Two-Wheeler Commute | B80: 0 | C80: km | D80: 0.04 | E80: Not Yet Assessed | F80: =IF(B80=0,0,(B80*0.04)/1000) | G80: =IF(AND(B80>0,E80="Not Yet Assessed"),"Quantity entered but Data Quality not assessed",IF(AND(B80>0,D80=0),"Zero emission factor - check DB_Master",""))
A81: Car Commute - Small Segment | B81: 0 | C81: km | D81: 0.11 | E81: Not Yet Assessed | F81: =IF(B81=0,0,(B81*0.11)/1000) | G81: =IF(AND(B81>0,E81="Not Yet Assessed"),"Quantity entered but Data Quality not assessed",IF(AND(B81>0,D81=0),"Zero emission factor - check DB_Master",""))
A82: Car Commute - Average | B82: 0 | C82: km | D82: 0.14 | E82: Not Yet Assessed | F82: =IF(B82=0,0,(B82*0.14)/1000) | G82: =IF(AND(B82>0,E82="Not Yet Assessed"),"Quantity entered but Data Quality not assessed",IF(AND(B82>0,D82=0),"Zero emission factor - check DB_Master",""))
A83: Car Commute - Large Segment | B83: 0 | C83: km | D83: 0.17 | E83: Not Yet Assessed | F83: =IF(B83=0,0,(B83*0.17)/1000) | G83: =IF(AND(B83>0,E83="Not Yet Assessed"),"Quantity entered but Data Quality not assessed",IF(AND(B83>0,D83=0),"Zero emission factor - check DB_Master",""))
A84: Bus Commute | B84: 0 | C84: p-km | D84: 0.03 | E84: Not Yet Assessed | F84: =IF(B84=0,0,(B84*0.03)/1000) | G84: =IF(AND(B84>0,E84="Not Yet Assessed"),"Quantity entered but Data Quality not assessed",IF(AND(B84>0,D84=0),"Zero emission factor - check DB_Master",""))
A85: Metro Rail Commute | B85: 0 | C85: p-km | D85: 0.015 | E85: Not Yet Assessed | F85: =IF(B85=0,0,(B85*0.015)/1000) | G85: =IF(AND(B85>0,E85="Not Yet Assessed"),"Quantity entered but Data Quality not assessed",IF(AND(B85>0,D85=0),"Zero emission factor - check DB_Master",""))
A86: Category 8: Upstream Leased Assets [CAUTION: CAUTION: include only assets NOT already captured in Scope 1/2 under your Cover_Boundary consolidation approach - avoid double counting]
A87: Leased Office/Warehouse Electricity | B87: 0 | C87: kWh | D87: 0.7314 | E87: Not Yet Assessed | F87: =IF(B87=0,0,(B87*0.7314)/1000) | G87: =IF(AND(B87>0,E87="Not Yet Assessed"),"Quantity entered but Data Quality not assessed",IF(AND(B87>0,D87=0),"Zero emission factor - check DB_Master",""))
A88: Leased Facility Water Use | B88: 0 | C88: m3 | D88: 0.31 | E88: Not Yet Assessed | F88: =IF(B88=0,0,(B88*0.31)/1000) | G88: =IF(AND(B88>0,E88="Not Yet Assessed"),"Quantity entered but Data Quality not assessed",IF(AND(B88>0,D88=0),"Zero emission factor - check DB_Master",""))
A89: Category 9: Downstream Transportation & Distribution
A90: Outbound Trucking to Customers | B90: 0 | C90: tonne-km | D90: 0.09 | E90: Not Yet Assessed | F90: =IF(B90=0,0,(B90*0.09)/1000) | G90: =IF(AND(B90>0,E90="Not Yet Assessed"),"Quantity entered but Data Quality not assessed",IF(AND(B90>0,D90=0),"Zero emission factor - check DB_Master",""))
A91: Outbound Air Freight to Customers | B91: 0 | C91: tonne-km | D91: 1.58 | E91: Not Yet Assessed | F91: =IF(B91=0,0,(B91*1.58)/1000) | G91: =IF(AND(B91>0,E91="Not Yet Assessed"),"Quantity entered but Data Quality not assessed",IF(AND(B91>0,D91=0),"Zero emission factor - check DB_Master",""))
A92: Outbound Rail Distribution | B92: 0 | C92: tonne-km | D92: 0.015 | E92: Not Yet Assessed | F92: =IF(B92=0,0,(B92*0.015)/1000) | G92: =IF(AND(B92>0,E92="Not Yet Assessed"),"Quantity entered but Data Quality not assessed",IF(AND(B92>0,D92=0),"Zero emission factor - check DB_Master",""))

Sheet Materiality_Screening
A1: # | B1: Scope 3 Category | C1: Where it's calculated | D1: Screening Decision | E1: Justification (required if Excluded / N/A)
A2: 1 | B2: Category 1: Purchased Goods & Services | C2: Covered in GHG_Calculator (spend + material proxies) | D2: Included
A3: 2 | B3: Category 2: Capital Goods | C3: Covered in GHG_Calculator | D3: Included
A4: 3 | B4: Category 3: Fuel- and Energy-Related Activities (not in Scope 1/2) | C4: Covered in GHG_Calculator | D4: Included
A5: 4 | B5: Category 4: Upstream Transportation & Distribution | C5: Covered in GHG_Calculator | D5: Included
A6: 5 | B6: Category 5: Waste Generated in Operations | C6: Covered in GHG_Calculator | D6: Included
A7: 6 | B7: Category 6: Business Travel | C7: Covered in GHG_Calculator | D7: Included
A8: 7 | B8: Category 7: Employee Commuting | C8: Covered in GHG_Calculator | D8: Included
A9: 8 | B9: Category 8: Upstream Leased Assets | C9: Covered in GHG_Calculator | D9: Included
A10: 9 | B10: Category 9: Downstream Transportation & Distribution | C10: Covered in GHG_Calculator | D10: Included
A11: 10 | B11: Category 10: Processing of Sold Products | C11: Scope3_Hard_Categories tab | D11: Included
A12: 11 | B12: Category 11: Use of Sold Products | C12: Scope3_Hard_Categories tab | D12: Included
A13: 12 | B13: Category 12: End-of-Life Treatment of Sold Products | C13: Scope3_Hard_Categories tab | D13: Included
... A16: 15 | B16: Category 15: Investments | C16: Scope3_Hard_Categories tab | D16: Included
A18: A category can only be left out of the Dashboard total by an explicit 'Excluded' or 'Not Applicable' decision with a stated reason here — nothing is omitted silently. The Dashboard lists excluded categories with their justification alongside the total.

Sheet Scope3_Hard_Categories
A1: Scope 3 Categories 10-15 — Guided Calculators
A2: These categories can't be estimated from a universal emission factor — each depends on your own product or company data. Fill in the yellow input cells; results calculate live. If you don't have the data yet, go mark the category 'Excluded' in Materiality_Screening with a reason rather than leaving zeros here.
A4: Category 10: Processing of Sold Products
A5: Input | B5: Value | C5: Unit
A6: Units sold requiring further processing | B6: 0 | C6: Units
A7: Downstream processing energy per unit | B7: 0 | C7: kWh/unit
A8: Grid emission factor (auto, from DB_Master) | B8: =VLOOKUP("Grid_India_CEA", DB_Master!$A:$B, 2, 0) | C8: kgCO2e/kWh
A9: RESULT: Category 10 (tCO2e) | B9: =(B6*B7*B8)/1000
A11: Category 11: Use of Sold Products
A12: Input | B12: Value | C12: Unit
A13: Units sold | B13: 0 | C13: Units
A14: In-use energy draw per unit per year | B14: 0 | C14: kWh/unit/year
A15: Expected product lifetime | B15: 0 | C15: Years
A16: Grid emission factor (auto, from DB_Master) | B16: =VLOOKUP("Grid_India_CEA", DB_Master!$A:$B, 2, 0) | C16: kgCO2e/kWh
A17: RESULT: Category 11 (tCO2e) | B17: =(B13*B14*B15*B16)/1000
A19: Category 12: End-of-Life Treatment of Sold Products
A20: Input | B20: Value | C20: Unit
A21: Units sold | B21: 0 | C21: Units
A22: Weight per unit | B22: 0 | C22: kg/unit
A23: Share disposed to landfill | B23: 0 | C23: % (0-1)
A24: Share recycled | B24: 0 | C24: % (0-1)
A25: Share incinerated | B25: 0 | C25: % (0-1)
A26: Check: shares must sum to 100% | B26: =IF(SUM(B23:B25)=1,"OK","FIX: shares do not sum to 100%")
A27: Landfill factor (auto, from DB_Master) | B27: =VLOOKUP("Waste_Landfill", DB_Master!$A:$B, 2, 0) | C27: kgCO2e/kg
A28: Recycling factor (auto, from DB_Master) | B28: =VLOOKUP("Waste_Recycle", DB_Master!$A:$B, 2, 0) | C28: kgCO2e/kg
A29: Incineration factor (auto, from DB_Master) | B29: =VLOOKUP("Waste_Incineration", DB_Master!$A:$B, 2, 0) | C29: kgCO2e/kg
A30: RESULT: Category 12 (tCO2e) | B30: =(B21*B22*(B23*B27+B24*B28+B25*B29))/1000
A32: Category 13: Downstream Leased Assets
A33: Input | B33: Value | C33: Unit
A34: Energy use of assets leased OUT to others (not already in Scope 1/2) | B34: 0 | C34: kWh
A35: Grid emission factor (auto, from DB_Master) | B35: =VLOOKUP("Grid_India_CEA", DB_Master!$A:$B, 2, 0) | C35: kgCO2e/kWh
A36: RESULT: Category 13 (tCO2e) | B36: =(B34*B35)/1000
A38: Category 14: Franchises
A39: Input | B39: Value | C39: Unit
A40: Number of franchises | B40: 0 | C40: Franchises
A41: Average emissions per franchise (company-reported or estimated) | B41: 0 | C41: tCO2e/franchise
A42: RESULT: Category 14 (tCO2e) | B42: =B40*B41
A44: Category 15: Investments
A45: Investee | B45: Investee Emissions (tCO2e) | C45: Equity Share (0-1) | D45: Attributed Emissions (tCO2e)
A46: Investee 1 | B46: 0 | C46: 0 | D46: =B46*C46
A47: Investee 2 | B47: 0 | C47: 0 | D47: =B47*C47
A48: Investee 3 | B48: 0 | C48: 0 | D48: =B48*C48
A49: Investee 4 | B49: 0 | C49: 0 | D49: =B49*C49
A50: Investee 5 | B50: 0 | C50: 0 | D50: =B50*C50
A51: RESULT: Category 15 (tCO2e) | B51: =SUM(D46:D50)
A53: SCOPE 3 CATEGORIES 10-15 TOTAL (tCO2e) | B53: =B9+B17+B30+B36+B42+B51

Sheet _chart_data
A1: Bucket | B1: tCO2e
A2: Scope 1 | B2: =Dashboard!B4
A3: Scope 2 (Location-Based) | B3: =Dashboard!B5
A4: Scope 3 Cat 1-9 | B4: =Dashboard!B7
A5: Scope 3 Cat 10-15 | B5: =Dashboard!B8
